{
  "n_rows": 2651,
  "n_cols": 1955,
  "resolution": 2.0,
  "bounds": {
    "x_min": 659.1376719786979,
    "x_max": 4569.137671978698,
    "y_min": -3987.027002959573,
    "y_max": 1314.972997040427,
    "min_lat": 33.1541840908825,
    "max_lat": 33.20181254938053,
    "min_lon": -117.392924613082,
    "max_lon": -117.35095346801556
  },
  "origin": {
    "lat": 33.19,
    "lon": -117.4
  },
  "nodata_value": -9999.0,
  "point_count": 11199,
  "elevation_stats": {
    "min": -38.56241255426882,
    "max": -7.741708361614741,
    "mean": -30.539497985361788
  },
  "valid_cell_count": 336354,
  "total_cell_count": 5182705,
  "survey_date": "2024-11-16"
}